tctools/__init__.py
tctools/__main__.py
tctools/common.py
tctools/format/__init__.py
tctools/format/__main__.py
tctools/format/format_class.py
tctools/format/format_extras.py
tctools/format/format_rules.py
tctools/git_info/__init__.py
tctools/git_info/__main__.py
tctools/git_info/git_info_class.py
tctools/make_release/__init__.py
tctools/make_release/__main__.py
tctools/make_release/make_release_class.py
tctools/xml_sort/__init__.py
tctools/xml_sort/__main__.py
tctools/xml_sort/xml_sort_class.py
twincat_tools-0.1.5.dist-info/entry_points.txt
twincat_tools-0.1.5.dist-info/METADATA
twincat_tools-0.1.5.dist-info/WHEEL
twincat_tools-0.1.5.dist-info/RECORD
