Metadata-Version: 2.1
Name: twincat-tools
Version: 0.1.5
Summary: A set of tools for TwinCAT projects
License: BSD-4-Clause
Author: Robert Roos
Author-email: robert.soor@gmail.com
Requires-Python: >=3.10,<4.0
Classifier: License :: Other/Proprietary License
Classifier: Programming Language :: Python :: 3
Classifier: Programming Language :: Python :: 3.10
Classifier: Programming Language :: Python :: 3.11
Classifier: Programming Language :: Python :: 3.12
Classifier: Programming Language :: Python :: 3.13
Requires-Dist: EditorConfig (>=0.12.4,<0.13.0)
Requires-Dist: GitPython (>=3.1.43,<4.0.0)
Requires-Dist: lxml (>=5.3.0,<6.0.0)
Requires-Dist: tomli (>=2.0.2,<3.0.0) ; python_version < "3.11"
Project-URL: Bug Tracker, https://github.com/DEMCON/twincat-tools/issues
Project-URL: Documentation, https://twincat-tools.readthedocs.io
Project-URL: Homepage, https://github.com/DEMCON/twincat-tools
